<?xml version="1.0" encoding="UTF-8"?>
<objects serializationModel="Studio.02.02.00">
	<object class="ParameterPreset" id="{2643baca-2d84-4bb5-9d07-812622925486}">
		<property name="name">
			<value>B-3 1 Active</value>
		</property>
		<relationship name="folder">
			<destination>{c8af1656-9543-490d-9f92-71fa3c25838b}</destination>
		</relationship>
		<relationship name="parameter">
			<destination>{324739cf-0e15-4b9f-af70-6a97b1b31e8a}</destination>
		</relationship>
	</object>
	<object class="GameParameter" id="{324739cf-0e15-4b9f-af70-6a97b1b31e8a}">
		<property name="parameterType">
			<value>1</value>
		</property>
		<property name="maximum">
			<value>2</value>
		</property>
		<property name="initialValue">
			<value>0</value>
		</property>
	</object>
</objects>
