<?xml version="1.0" encoding="UTF-8"?>
<objects serializationModel="Studio.02.02.00">
	<object class="ParameterPreset" id="{28eb0b19-98a0-47c3-b2e8-fbae40bab9a1}">
		<property name="name">
			<value>Rec E 2 Active</value>
		</property>
		<relationship name="folder">
			<destination>{c8af1656-9543-490d-9f92-71fa3c25838b}</destination>
		</relationship>
		<relationship name="parameter">
			<destination>{14fb47d5-b151-437c-9e4a-64a78b2be2c2}</destination>
		</relationship>
	</object>
	<object class="GameParameter" id="{14fb47d5-b151-437c-9e4a-64a78b2be2c2}">
		<property name="parameterType">
			<value>1</value>
		</property>
		<property name="maximum">
			<value>2</value>
		</property>
		<property name="initialValue">
			<value>0</value>
		</property>
	</object>
</objects>
