<?xml version="1.0" encoding="UTF-8"?>
<objects serializationModel="Studio.02.02.00">
	<object class="AudioFile" id="{7a608cbd-9e92-4cce-905b-becd3c23d458}">
		<property name="assetPath">
			<value>207457__aureliosons__avion-de-elices.wav</value>
		</property>
		<property name="isStreaming">
			<value>true</value>
		</property>
		<property name="frequencyInKHz">
			<value>96</value>
		</property>
		<property name="channelCount">
			<value>2</value>
		</property>
		<property name="length">
			<value>13.317333333333334</value>
		</property>
		<relationship name="masterAssetFolder">
			<destination>{f68a1cd6-e0d4-4b46-8ddb-ab6d82ac74b4}</destination>
		</relationship>
	</object>
</objects>
